kicad_assistant/__init__.py
kicad_assistant/mcp_server.py
kicad_assistant/board/__init__.py
kicad_assistant/board/analyzer.py
kicad_assistant/board/dfm.py
kicad_assistant/board/fixer.py
kicad_assistant/board/layers.py
kicad_assistant/board/zones.py
kicad_assistant/presets/__init__.py
kicad_assistant/presets/jlcpcb.py
kicad_assistant/presets/oshpark.py
kicad_assistant/presets/pcbway.py
kicad_assistant/project/__init__.py
kicad_assistant/project/bom.py
kicad_assistant/project/loader.py
kicad_assistant/schematic/__init__.py
kicad_assistant/schematic/analyzer.py
kicad_assistant/schematic/erc.py
kicad_assistant/utils/__init__.py
kicad_assistant/utils/backup.py
kicad_assistant/utils/geometry.py
kicad_assistant-2.0.0.dist-info/LICENSE
kicad_assistant-2.0.0.dist-info/METADATA
kicad_assistant-2.0.0.dist-info/WHEEL
kicad_assistant-2.0.0.dist-info/entry_points.txt
kicad_assistant-2.0.0.dist-info/top_level.txt
kicad_assistant-2.0.0.dist-info/RECORD
