Metadata-Version: 2.1
Name: kicad-assistant
Version: 2.0.0
Summary: AI-powered design review and repair for KiCad PCB projects
Author: KiCad Assistant Contributors
License: MIT
Project-URL: Homepage, https://github.com/cohen5/kicad-assistant
Project-URL: Repository, https://github.com/cohen5/kicad-assistant
Project-URL: Issues, https://github.com/cohen5/kicad-assistant/issues
Keywords: kicad,pcb,eda,electronics,dfm,mcp,claude
Classifier: Development Status :: 4 - Beta
Classifier: Intended Audience :: Developers
Classifier: Intended Audience :: Manufacturing
Classifier: Programming Language :: Python :: 3
Classifier: Programming Language :: Python :: 3.10
Classifier: Programming Language :: Python :: 3.11
Classifier: Programming Language :: Python :: 3.12
Classifier: Topic :: Scientific/Engineering :: Electronic Design Automation (EDA)
Requires-Python: >=3.10
License-File: LICENSE
Requires-Dist: kiutils>=1.4.0
Requires-Dist: mcp>=0.9.0
Provides-Extra: dev
Requires-Dist: pytest>=7.0; extra == "dev"
Requires-Dist: pytest-asyncio>=0.21; extra == "dev"
